{"question_id": "526", "problem_slug": "beautiful-arrangement", "problem_title": "Beautiful Arrangement", "content": "Suppose you have n integers labeled 1 through n. A permutation of those n integers perm (1-indexed) is considered a beautiful arrangement if for every i (1 <= i <= n), either of the following is true:\n\nperm[i] is divisible by i.\ni is divisible by perm[i].\n\nGiven an integer n, return the number of the beautiful arrangements that you can construct.\n \nExample 1:\n\nInput: n = 2\nOutput: 2\nExplanation: \nThe first beautiful arrangement is [1,2]:\n    - perm[1] = 1 is divisible by i = 1\n    - perm[2] = 2 is divisible by i = 2\nThe second beautiful arrangement is [2,1]:\n    - perm[1] = 2 is divisible by i = 1\n    - i = 2 is divisible by perm[2] = 1\n\nExample 2:\n\nInput: n = 1\nOutput: 1\n\n \nConstraints:\n\n1 <= n <= 15\n\n", "hints": [], "exampleTestcases": "2\n1", "codeSnippets": {"C++": {"langSlug": "cpp", "code": "class Solution {\npublic:\n    int countArrangement(int n) {\n        \n    }\n};"}, "Java": {"langSlug": "java", "code": "class Solution {\n    public int countArrangement(int n) {\n        \n    }\n}"}, "Python": {"langSlug": "python", "code": "class Solution(object):\n    def countArrangement(self, n):\n        \"\"\"\n        :type n: int\n        :rtype: int\n        \"\"\"\n        "}, "Python3": {"langSlug": "python3", "code": "class Solution:\n    def countArrangement(self, n: int) -> int:\n        "}, "C": {"langSlug": "c", "code": "int countArrangement(int n) {\n    \n}"}, "C#": {"langSlug": "csharp", "code": "public class Solution {\n    public int CountArrangement(int n) {\n        \n    }\n}"}, "JavaScript": {"langSlug": "javascript", "code": "/**\n * @param {number} n\n * @return {number}\n */\nvar countArrangement = function(n) {\n    \n};"}, "TypeScript": {"langSlug": "typescript", "code": "function countArrangement(n: number): number {\n    \n};"}, "PHP": {"langSlug": "php", "code": "class Solution {\n\n    /**\n     * @param Integer $n\n     * @return Integer\n     */\n    function countArrangement($n) {\n        \n    }\n}"}, "Swift": {"langSlug": "swift", "code": "class Solution {\n    func countArrangement(_ n: Int) -> Int {\n        \n    }\n}"}, "Kotlin": {"langSlug": "kotlin", "code": "class Solution {\n    fun countArrangement(n: Int): Int {\n        \n    }\n}"}, "Dart": {"langSlug": "dart", "code": "class Solution {\n  int countArrangement(int n) {\n    \n  }\n}"}, "Go": {"langSlug": "golang", "code": "func countArrangement(n int) int {\n    \n}"}, "Ruby": {"langSlug": "ruby", "code": "# @param {Integer} n\n# @return {Integer}\ndef count_arrangement(n)\n    \nend"}, "Scala": {"langSlug": "scala", "code": "object Solution {\n    def countArrangement(n: Int): Int = {\n        \n    }\n}"}, "Rust": {"langSlug": "rust", "code": "impl Solution {\n    pub fn count_arrangement(n: i32) -> i32 {\n        \n    }\n}"}, "Racket": {"langSlug": "racket", "code": "(define/contract (count-arrangement n)\n  (-> exact-integer? exact-integer?)\n  )"}, "Erlang": {"langSlug": "erlang", "code": "-spec count_arrangement(N :: integer()) -> integer().\ncount_arrangement(N) ->\n  ."}, "Elixir": {"langSlug": "elixir", "code": "defmodule Solution do\n  @spec count_arrangement(n :: integer) :: integer\n  def count_arrangement(n) do\n    \n  end\nend"}}}