{"questionId": "3369", "acRate": 78.65404837013669, "difficulty": "Hard", "freqBar": 0.0, "frontendQuestionId": "3061", "paidOnly": true, "status": "ac", "title": "Calculate Trapping Rain Water", "topicTags": [{"name": "Database", "id": "VG9waWNUYWdOb2RlOjYxMDQz", "slug": "database"}], "titleSlug": "calculate-trapping-rain-water", "content": "<p>Table: <font face=\"monospace\">Heights</font></p>\n\n<pre>\n+-------------+------+\n| Column Name | Type |\n+-------------+------+\n| id          | int  |\n| height      | int  |\n+-------------+------+\nid is the primary key (column with unique values) for this table, and it is guaranteed to be in sequential order.\nEach row of this table contains an id and height.\n</pre>\n\n<p>Write a solution to calculate the amount of rainwater can be <strong>trapped between the bars</strong> in the landscape, considering that each bar has a <strong>width</strong> of <code>1</code> unit.</p>\n\n<p>Return <em>the result table in </em><strong>any</strong><em> order.</em></p>\n\n<p>The result format is in the following example.</p>\n\n<p>&nbsp;</p>\n<p><strong class=\"example\">Example 1:</strong></p>\n\n<pre>\n<strong>Input:</strong> \nHeights table:\n+-----+--------+\n| id  | height |\n+-----+--------+\n| 1   | 0      |\n| 2   | 1      |\n| 3   | 0      |\n| 4   | 2      |\n| 5   | 1      |\n| 6   | 0      |\n| 7   | 1      |\n| 8   | 3      |\n| 9   | 2      |\n| 10  | 1      |\n| 11  | 2      |\n| 12  | 1      |\n+-----+--------+\n<strong>Output:</strong> \n+---------------------+\n| total_trapped_water | \n+---------------------+\n| 6                   | \n+---------------------+\n<strong>Explanation:</strong> \n<img src=\"https://assets.leetcode.com/uploads/2024/02/26/trapping_rain_water.png\" style=\"width:500px; height:200px;\" />\n\nThe elevation map depicted above (in the black section) is graphically represented with the x-axis denoting the id and the y-axis representing the heights [0,1,0,2,1,0,1,3,2,1,2,1]. In this scenario, 6 units of rainwater are trapped within the blue section.\n</pre>\n", "hints": [], "exampleTestcases": "{\"headers\":{\"Heights\":[\"id\",\"height\"]},\"rows\":{\"Heights\":[[1,0],[2,1],[3,0],[4,2],[5,1],[6,0],[7,1],[8,3],[9,2],[10,1],[11,2],[12,1]]}}", "codeSnippets": [{"lang": "MySQL", "langSlug": "mysql", "code": "# Write your MySQL query statement below\n"}, {"lang": "MS SQL Server", "langSlug": "mssql", "code": "/* Write your T-SQL query statement below */\n"}, {"lang": "Oracle", "langSlug": "oraclesql", "code": "/* Write your PL/SQL query statement below */\n"}, {"lang": "Pandas", "langSlug": "pythondata", "code": "import pandas as pd\n\ndef calculate_trapped_rain_water(heights: pd.DataFrame) -> pd.DataFrame:\n    "}, {"lang": "PostgreSQL", "langSlug": "postgresql", "code": "-- Write your PostgreSQL query statement below\n"}], "similarQuestionList": []}