{"question_id": "584", "problem_slug": "find-customer-referee", "problem_title": "Find Customer Referee", "content": "Table: Customer\n\n+-------------+---------+\n| Column Name | Type    |\n+-------------+---------+\n| id          | int     |\n| name        | varchar |\n| referee_id  | int     |\n+-------------+---------+\nIn SQL, id is the primary key column for this table.\nEach row of this table indicates the id of a customer, their name, and the id of the customer who referred them.\n\n \nFind the names of the customer that are not referred by the customer with id = 2.\nReturn the result table in any order.\nThe result format is in the following example.\n \nExample 1:\n\nInput: \nCustomer table:\n+----+------+------------+\n| id | name | referee_id |\n+----+------+------------+\n| 1  | Will | null       |\n| 2  | Jane | null       |\n| 3  | Alex | 2          |\n| 4  | Bill | null       |\n| 5  | Zack | 1          |\n| 6  | Mark | 2          |\n+----+------+------------+\nOutput: \n+------+\n| name |\n+------+\n| Will |\n| Jane |\n| Bill |\n| Zack |\n+------+\n\n", "hints": ["Be careful of the NULL value"], "exampleTestcases": "{\"headers\":{\"Customer\":[\"id\",\"name\",\"referee_id\"]},\"rows\":{\"Customer\":[[1,\"Will\",null],[2,\"Jane\",null],[3,\"Alex\",2],[4,\"Bill\",null],[5,\"Zack\",1],[6,\"Mark\",2]]}}", "codeSnippets": {"MySQL": {"langSlug": "mysql", "code": "# Write your MySQL query statement below\n"}, "MS SQL Server": {"langSlug": "mssql", "code": "/* Write your T-SQL query statement below */\n"}, "Oracle": {"langSlug": "oraclesql", "code": "/* Write your PL/SQL query statement below */\n"}, "Pandas": {"langSlug": "pythondata", "code": "import pandas as pd\n\ndef find_customer_referee(customer: pd.DataFrame) -> pd.DataFrame:\n    "}, "PostgreSQL": {"langSlug": "postgresql", "code": "-- Write your PostgreSQL query statement below\n"}}}