{"questionId": "2077", "acRate": 36.36639624900913, "difficulty": "Medium", "freqBar": 0.0, "frontendQuestionId": "1946", "paidOnly": false, "status": "ac", "title": "Largest Number After Mutating Substring", "topicTags": [{"name": "Array", "id": "VG9waWNUYWdOb2RlOjU=", "slug": "array"}, {"name": "String", "id": "VG9waWNUYWdOb2RlOjEw", "slug": "string"}, {"name": "Greedy", "id": "VG9waWNUYWdOb2RlOjE3", "slug": "greedy"}], "titleSlug": "largest-number-after-mutating-substring", "content": "<p>You are given a string <code>num</code>, which represents a large integer. You are also given a <strong>0-indexed</strong> integer array <code>change</code> of length <code>10</code> that maps each digit <code>0-9</code> to another digit. More formally, digit <code>d</code> maps to digit <code>change[d]</code>.</p>\n\n<p>You may <strong>choose</strong> to <b>mutate a single substring</b> of <code>num</code>. To mutate a substring, replace each digit <code>num[i]</code> with the digit it maps to in <code>change</code> (i.e. replace <code>num[i]</code> with <code>change[num[i]]</code>).</p>\n\n<p>Return <em>a string representing the <strong>largest</strong> possible integer after <strong>mutating</strong> (or choosing not to) a <strong>single substring</strong> of </em><code>num</code>.</p>\n\n<p>A <strong>substring</strong> is a contiguous sequence of characters within the string.</p>\n\n<p>&nbsp;</p>\n<p><strong class=\"example\">Example 1:</strong></p>\n\n<pre>\n<strong>Input:</strong> num = &quot;<u>1</u>32&quot;, change = [9,8,5,0,3,6,4,2,6,8]\n<strong>Output:</strong> &quot;<u>8</u>32&quot;\n<strong>Explanation:</strong> Replace the substring &quot;1&quot;:\n- 1 maps to change[1] = 8.\nThus, &quot;<u>1</u>32&quot; becomes &quot;<u>8</u>32&quot;.\n&quot;832&quot; is the largest number that can be created, so return it.\n</pre>\n\n<p><strong class=\"example\">Example 2:</strong></p>\n\n<pre>\n<strong>Input:</strong> num = &quot;<u>021</u>&quot;, change = [9,4,3,5,7,2,1,9,0,6]\n<strong>Output:</strong> &quot;<u>934</u>&quot;\n<strong>Explanation:</strong> Replace the substring &quot;021&quot;:\n- 0 maps to change[0] = 9.\n- 2 maps to change[2] = 3.\n- 1 maps to change[1] = 4.\nThus, &quot;<u>021</u>&quot; becomes &quot;<u>934</u>&quot;.\n&quot;934&quot; is the largest number that can be created, so return it.\n</pre>\n\n<p><strong class=\"example\">Example 3:</strong></p>\n\n<pre>\n<strong>Input:</strong> num = &quot;5&quot;, change = [1,4,7,5,3,2,5,6,9,4]\n<strong>Output:</strong> &quot;5&quot;\n<strong>Explanation:</strong> &quot;5&quot; is already the largest number that can be created, so return it.\n</pre>\n\n<p>&nbsp;</p>\n<p><strong>Constraints:</strong></p>\n\n<ul>\n\t<li><code>1 &lt;= num.length &lt;= 10<sup>5</sup></code></li>\n\t<li><code>num</code> consists of only digits <code>0-9</code>.</li>\n\t<li><code>change.length == 10</code></li>\n\t<li><code>0 &lt;= change[d] &lt;= 9</code></li>\n</ul>\n", "hints": ["Should you change a digit if the new digit is smaller than the original?", "If changing the first digit and the last digit both make the number bigger, but you can only change one of them; which one should you change?", "Changing numbers closer to the front is always better"], "exampleTestcases": "\"132\"\n[9,8,5,0,3,6,4,2,6,8]\n\"021\"\n[9,4,3,5,7,2,1,9,0,6]\n\"5\"\n[1,4,7,5,3,2,5,6,9,4]", "codeSnippets": [{"lang": "C++", "langSlug": "cpp", "code": "class Solution {\npublic:\n    string maximumNumber(string num, vector<int>& change) {\n        \n    }\n};"}, {"lang": "Java", "langSlug": "java", "code": "class Solution {\n    public String maximumNumber(String num, int[] change) {\n        \n    }\n}"}, {"lang": "Python", "langSlug": "python", "code": "class Solution(object):\n    def maximumNumber(self, num, change):\n        \"\"\"\n        :type num: str\n        :type change: List[int]\n        :rtype: str\n        \"\"\"\n        "}, {"lang": "Python3", "langSlug": "python3", "code": "class Solution:\n    def maximumNumber(self, num: str, change: List[int]) -> str:\n        "}, {"lang": "C", "langSlug": "c", "code": "char* maximumNumber(char* num, int* change, int changeSize) {\n    \n}"}, {"lang": "C#", "langSlug": "csharp", "code": "public class Solution {\n    public string MaximumNumber(string num, int[] change) {\n        \n    }\n}"}, {"lang": "JavaScript", "langSlug": "javascript", "code": "/**\n * @param {string} num\n * @param {number[]} change\n * @return {string}\n */\nvar maximumNumber = function(num, change) {\n    \n};"}, {"lang": "TypeScript", "langSlug": "typescript", "code": "function maximumNumber(num: string, change: number[]): string {\n    \n};"}, {"lang": "PHP", "langSlug": "php", "code": "class Solution {\n\n    /**\n     * @param String $num\n     * @param Integer[] $change\n     * @return String\n     */\n    function maximumNumber($num, $change) {\n        \n    }\n}"}, {"lang": "Swift", "langSlug": "swift", "code": "class Solution {\n    func maximumNumber(_ num: String, _ change: [Int]) -> String {\n        \n    }\n}"}, {"lang": "Kotlin", "langSlug": "kotlin", "code": "class Solution {\n    fun maximumNumber(num: String, change: IntArray): String {\n        \n    }\n}"}, {"lang": "Dart", "langSlug": "dart", "code": "class Solution {\n  String maximumNumber(String num, List<int> change) {\n    \n  }\n}"}, {"lang": "Go", "langSlug": "golang", "code": "func maximumNumber(num string, change []int) string {\n    \n}"}, {"lang": "Ruby", "langSlug": "ruby", "code": "# @param {String} num\n# @param {Integer[]} change\n# @return {String}\ndef maximum_number(num, change)\n    \nend"}, {"lang": "Scala", "langSlug": "scala", "code": "object Solution {\n    def maximumNumber(num: String, change: Array[Int]): String = {\n        \n    }\n}"}, {"lang": "Rust", "langSlug": "rust", "code": "impl Solution {\n    pub fn maximum_number(num: String, change: Vec<i32>) -> String {\n        \n    }\n}"}, {"lang": "Racket", "langSlug": "racket", "code": "(define/contract (maximum-number num change)\n  (-> string? (listof exact-integer?) string?)\n  )"}, {"lang": "Erlang", "langSlug": "erlang", "code": "-spec maximum_number(Num :: unicode:unicode_binary(), Change :: [integer()]) -> unicode:unicode_binary().\nmaximum_number(Num, Change) ->\n  ."}, {"lang": "Elixir", "langSlug": "elixir", "code": "defmodule Solution do\n  @spec maximum_number(num :: String.t, change :: [integer]) :: String.t\n  def maximum_number(num, change) do\n    \n  end\nend"}], "similarQuestionList": []}