{"question_id": "234", "problem_slug": "palindrome-linked-list", "problem_title": "Palindrome Linked List", "content": "Given the head of a singly linked list, return true if it is a palindrome or false otherwise.\n \nExample 1:\n\n\nInput: head = [1,2,2,1]\nOutput: true\n\nExample 2:\n\n\nInput: head = [1,2]\nOutput: false\n\n \nConstraints:\n\nThe number of nodes in the list is in the range [1, 105].\n0 <= Node.val <= 9\n\n \nFollow up: Could you do it in O(n) time and O(1) space?", "hints": [], "exampleTestcases": "[1,2,2,1]\n[1,2]", "codeSnippets": {"C++": {"langSlug": "cpp", "code": "/**\n * Definition for singly-linked list.\n * struct ListNode {\n *     int val;\n *     ListNode *next;\n *     ListNode() : val(0), next(nullptr) {}\n *     ListNode(int x) : val(x), next(nullptr) {}\n *     ListNode(int x, ListNode *next) : val(x), next(next) {}\n * };\n */\nclass Solution {\npublic:\n    bool isPalindrome(ListNode* head) {\n        \n    }\n};"}, "Java": {"langSlug": "java", "code": "/**\n * Definition for singly-linked list.\n * public class ListNode {\n *     int val;\n *     ListNode next;\n *     ListNode() {}\n *     ListNode(int val) { this.val = val; }\n *     ListNode(int val, ListNode next) { this.val = val; this.next = next; }\n * }\n */\nclass Solution {\n    public boolean isPalindrome(ListNode head) {\n        \n    }\n}"}, "Python": {"langSlug": "python", "code": "# Definition for singly-linked list.\n# class ListNode(object):\n#     def __init__(self, val=0, next=None):\n#         self.val = val\n#         self.next = next\nclass Solution(object):\n    def isPalindrome(self, head):\n        \"\"\"\n        :type head: ListNode\n        :rtype: bool\n        \"\"\"\n        "}, "Python3": {"langSlug": "python3", "code": "# Definition for singly-linked list.\n# class ListNode:\n#     def __init__(self, val=0, next=None):\n#         self.val = val\n#         self.next = next\nclass Solution:\n    def isPalindrome(self, head: Optional[ListNode]) -> bool:\n        "}, "C": {"langSlug": "c", "code": "/**\n * Definition for singly-linked list.\n * struct ListNode {\n *     int val;\n *     struct ListNode *next;\n * };\n */\nbool isPalindrome(struct ListNode* head) {\n    \n}"}, "C#": {"langSlug": "csharp", "code": "/**\n * Definition for singly-linked list.\n * public class ListNode {\n *     public int val;\n *     public ListNode next;\n *     public ListNode(int val=0, ListNode next=null) {\n *         this.val = val;\n *         this.next = next;\n *     }\n * }\n */\npublic class Solution {\n    public bool IsPalindrome(ListNode head) {\n        \n    }\n}"}, "JavaScript": {"langSlug": "javascript", "code": "/**\n * Definition for singly-linked list.\n * function ListNode(val, next) {\n *     this.val = (val===undefined ? 0 : val)\n *     this.next = (next===undefined ? null : next)\n * }\n */\n/**\n * @param {ListNode} head\n * @return {boolean}\n */\nvar isPalindrome = function(head) {\n    \n};"}, "TypeScript": {"langSlug": "typescript", "code": "/**\n * Definition for singly-linked list.\n * class ListNode {\n *     val: number\n *     next: ListNode | null\n *     constructor(val?: number, next?: ListNode | null) {\n *         this.val = (val===undefined ? 0 : val)\n *         this.next = (next===undefined ? null : next)\n *     }\n * }\n */\n\nfunction isPalindrome(head: ListNode | null): boolean {\n    \n};"}, "PHP": {"langSlug": "php", "code": "/**\n * Definition for a singly-linked list.\n * class ListNode {\n *     public $val = 0;\n *     public $next = null;\n *     function __construct($val = 0, $next = null) {\n *         $this->val = $val;\n *         $this->next = $next;\n *     }\n * }\n */\nclass Solution {\n\n    /**\n     * @param ListNode $head\n     * @return Boolean\n     */\n    function isPalindrome($head) {\n        \n    }\n}"}, "Swift": {"langSlug": "swift", "code": "/**\n * Definition for singly-linked list.\n * public class ListNode {\n *     public var val: Int\n *     public var next: ListNode?\n *     public init() { self.val = 0; self.next = nil; }\n *     public init(_ val: Int) { self.val = val; self.next = nil; }\n *     public init(_ val: Int, _ next: ListNode?) { self.val = val; self.next = next; }\n * }\n */\nclass Solution {\n    func isPalindrome(_ head: ListNode?) -> Bool {\n        \n    }\n}"}, "Kotlin": {"langSlug": "kotlin", "code": "/**\n * Example:\n * var li = ListNode(5)\n * var v = li.`val`\n * Definition for singly-linked list.\n * class ListNode(var `val`: Int) {\n *     var next: ListNode? = null\n * }\n */\nclass Solution {\n    fun isPalindrome(head: ListNode?): Boolean {\n        \n    }\n}"}, "Dart": {"langSlug": "dart", "code": "/**\n * Definition for singly-linked list.\n * class ListNode {\n *   int val;\n *   ListNode? next;\n *   ListNode([this.val = 0, this.next]);\n * }\n */\nclass Solution {\n  bool isPalindrome(ListNode? head) {\n    \n  }\n}"}, "Go": {"langSlug": "golang", "code": "/**\n * Definition for singly-linked list.\n * type ListNode struct {\n *     Val int\n *     Next *ListNode\n * }\n */\nfunc isPalindrome(head *ListNode) bool {\n    \n}"}, "Ruby": {"langSlug": "ruby", "code": "# Definition for singly-linked list.\n# class ListNode\n#     attr_accessor :val, :next\n#     def initialize(val = 0, _next = nil)\n#         @val = val\n#         @next = _next\n#     end\n# end\n# @param {ListNode} head\n# @return {Boolean}\ndef is_palindrome(head)\n    \nend"}, "Scala": {"langSlug": "scala", "code": "/**\n * Definition for singly-linked list.\n * class ListNode(_x: Int = 0, _next: ListNode = null) {\n *   var next: ListNode = _next\n *   var x: Int = _x\n * }\n */\nobject Solution {\n    def isPalindrome(head: ListNode): Boolean = {\n        \n    }\n}"}, "Rust": {"langSlug": "rust", "code": "// Definition for singly-linked list.\n// #[derive(PartialEq, Eq, Clone, Debug)]\n// pub struct ListNode {\n//   pub val: i32,\n//   pub next: Option<Box<ListNode>>\n// }\n// \n// impl ListNode {\n//   #[inline]\n//   fn new(val: i32) -> Self {\n//     ListNode {\n//       next: None,\n//       val\n//     }\n//   }\n// }\nimpl Solution {\n    pub fn is_palindrome(head: Option<Box<ListNode>>) -> bool {\n        \n    }\n}"}, "Racket": {"langSlug": "racket", "code": "; Definition for singly-linked list:\n#|\n\n; val : integer?\n; next : (or/c list-node? #f)\n(struct list-node\n  (val next) #:mutable #:transparent)\n\n; constructor\n(define (make-list-node [val 0])\n  (list-node val #f))\n\n|#\n\n(define/contract (is-palindrome head)\n  (-> (or/c list-node? #f) boolean?)\n  )"}, "Erlang": {"langSlug": "erlang", "code": "%% Definition for singly-linked list.\n%%\n%% -record(list_node, {val = 0 :: integer(),\n%%                     next = null :: 'null' | #list_node{}}).\n\n-spec is_palindrome(Head :: #list_node{} | null) -> boolean().\nis_palindrome(Head) ->\n  ."}, "Elixir": {"langSlug": "elixir", "code": "# Definition for singly-linked list.\n#\n# defmodule ListNode do\n#   @type t :: %__MODULE__{\n#           val: integer,\n#           next: ListNode.t() | nil\n#         }\n#   defstruct val: 0, next: nil\n# end\n\ndefmodule Solution do\n  @spec is_palindrome(head :: ListNode.t | nil) :: boolean\n  def is_palindrome(head) do\n    \n  end\nend"}}}